ganymede/__init__.py
ganymede/lib.py
ganymede/editor/__init__.py
ganymede/editor/context.py
ganymede/editor/query.py
ganymede/editor/save.py
ganymede/editor/storage.py
ganymede/editor/util.py
ganymede/editor/tests/__init__.py
ganymede/editor/tests/test_editor.py
ganymede/notebook/__init__.py
ganymede/notebook/query.py
ganymede/notebook/save.py
ganymede/notebook/storage.py
ganymede/notebook/tests/__init__.py
ganymede/notebook/tests/test_notebook.py
ganymede_py-0.0.24.dist-info/LICENSE
ganymede_py-0.0.24.dist-info/METADATA
ganymede_py-0.0.24.dist-info/WHEEL
ganymede_py-0.0.24.dist-info/top_level.txt
ganymede_py-0.0.24.dist-info/RECORD
