Metadata-Version: 2.1
Name: ganymede-py
Version: 0.0.24
Summary: Ganymede Python libraries
License: Apache License
Project-URL: Homepage, https://github.com/Ganymede-Bio/pylib
Keywords: ganymede
Classifier: License :: OSI Approved :: MIT License
Classifier: Programming Language :: Python
Classifier: Programming Language :: Python :: 3
Requires-Python: >=3.7
License-File: LICENSE
Requires-Dist: nbformat
Requires-Dist: requests
Requires-Dist: setuptools
Requires-Dist: tomli
Requires-Dist: pandas-gbq
Requires-Dist: ipython
Requires-Dist: tqdm
Requires-Dist: grpcio (==1.50.0)
Requires-Dist: google-cloud-storage
Provides-Extra: dev
Requires-Dist: black ; extra == 'dev'
Requires-Dist: bumpver ; extra == 'dev'
Requires-Dist: isort ; extra == 'dev'
Requires-Dist: pip-tools ; extra == 'dev'
